{
  "analysis_timestamp": "2025-01-21T20:35:00Z",
  "total_files": 31,
  "file_categories": {
    "documentation": 26,
    "configuration": 4,
    "source_code": 1
  },
  "file_types": {
    "markdown": 26,
    "text": 4,
    "json": 1
  },
  "key_files": [
    "README.md",
    "BUILD_CONFIG.md", 
    "PROJECT_STRUCTURE.md",
    "capsule_brain/core/capsule_engine.py",
    "teacher/ai_overseer.py",
    "core_principles/alignment_core.txt"
  ],
  "architecture_components": [
    "CapsuleEngine - Main orchestrator",
    "BeliefStateManager - Working memory",
    "AlignmentCore - Ethical principles",
    "IITAnalyzer - Consciousness metrics",
    "SelfWirer - Self-modification",
    "AIOverseer - Supervisory system",
    "AdvancedGUI - Web interface"
  ],
  "deployment_options": [
    "Docker Compose",
    "Kubernetes Helm",
    "Terraform Infrastructure",
    "GitOps with ArgoCD"
  ],
  "monitoring_stack": [
    "Prometheus metrics",
    "Grafana dashboards", 
    "Alerting system",
    "Health checks"
  ]
}
